{
    "Event Handler (Airstrip Sink)": {
        "Structs": {
            "SinkInfo": {
                "Region": {
                    "Type": "INT",
                    "ArraySize": 1
                },
                "ClearCondition": {
                    "Type": "INT",
                    "ArraySize": 1
                }
            }
        },
        "Members": {
            "SinkCount": {
                "Type": "INT",
                "ArraySize": 1
            },
            "VTXStart": {
                "Type": "INT",
                "ArraySize": 1
            },
            "SinkInfo": {
                "Type": "SinkInfo",
                "ArraySize": "SinkCount"
            }
        },
        "Wizard": {
            "Default": {
                "SinkCount": 0,
                "VTXStart": 0,
                "SinkInfo": {
                    "Region": 0,
                    "ClearCondition": 1
                }
            }
        }
    }
}