{
    "Billboard": {
        "Members": {
            "Transform": {
                "Type": "TRANSFORM",
                "ArraySize": 1
            },
            "Character": {
                "Type": "STRING",
                "ArraySize": 1
            },
            "!!!": {
                "Type": "INT",
                "ArraySize": 1
            },
            "Model": {
                "Type": "STRING",
                "ArraySize": 1
            },
            "SpawnObjID": {
                "Type": "INT",
                "ArraySize": 1
            },
            "SpawnLength": {
                "Type": "FLOAT",
                "ArraySize": 1
            },
            "SpawnHeight": {
                "Type": "FLOAT",
                "ArraySize": 1
            },
            "SpawnDuration": {
                "Type": "INT",
                "ArraySize": 1
            },
            "billboard_sun": {
                "Type": "COMMENT",
                "ArraySize": 1
            },
            "billboard_dolphin": {
                "Type": "COMMENT",
                "ArraySize": 1
            },
            "billboard_restaurant": {
                "Type": "COMMENT",
                "ArraySize": 1
            },
            "billboard_fish": {
                "Type": "COMMENT",
                "ArraySize": 1
            }
        },
        "Wizard": {
            "Default": {
                "Transform": [
                    [
                        0,
                        0,
                        0
                    ],
                    [
                        0,
                        0,
                        0
                    ],
                    [
                        0,
                        0,
                        0
                    ]
                ],
                "Character": "Generated from Bin Editor Template by Junior's Toolbox",
                "!!!": 0,
                "Model": "Generated from Bin Editor Template by Junior's Toolbox",
                "SpawnObjID": 0,
                "SpawnLength": 0,
                "SpawnHeight": 0,
                "SpawnDuration": 0,
                "billboard_sun": "Generated from Bin Editor Template by Junior's Toolbox",
                "billboard_dolphin": "Generated from Bin Editor Template by Junior's Toolbox",
                "billboard_restaurant": "Generated from Bin Editor Template by Junior's Toolbox",
                "billboard_fish": "Generated from Bin Editor Template by Junior's Toolbox"
            }
        }
    }
}