{
    "Stage Event Info": {
        "Structs": {
            "LightInfo": {
                "ID": {
                    "Type": "INT",
                    "ArraySize": 1
                },
                "Name": {
                    "Type": "STRING",
                    "ArraySize": 1
                }
            }
        },
        "Members": {
            "Unknown": {
                "Type": "INT",
                "ArraySize": 1
            }
        },
        "Wizard": {
            "Default": {
                "Unknown": 0
            }
        }
    }
}